xiatl/__init__.py
xiatl/constants.py
xiatl/errors.py
xiatl/loading.py
xiatl/macro_signature.py
xiatl/node.py
xiatl/node_reference.py
xiatl/processing.py
xiatl/resolution.py
xiatl/utilities.py
xiatl/parsing/__init__.py
xiatl/parsing/grammar.peg
xiatl/parsing/parser.py
xiatl/parsing/utilities.py
xiatl/parsing/pegboard/__init__.py
xiatl/parsing/pegboard/core/constants.py
xiatl/parsing/pegboard/core/parse_node.py
xiatl/parsing/pegboard/core/parse_result.py
xiatl/parsing/pegboard/core/parser.py
xiatl/parsing/pegboard/core/transforms.py
xiatl/parsing/pegboard/core/utilities.py
xiatl/parsing/pegboard/syntax/grammar.py
xiatl/parsing/pegboard/syntax/transforms.py
xiatl-0.1.1.dist-info/METADATA
xiatl-0.1.1.dist-info/WHEEL
xiatl-0.1.1.dist-info/licenses/LICENSE.txt
xiatl-0.1.1.dist-info/RECORD
