Metadata-Version: 2.4
Name: xiatl
Version: 0.1.1
Summary: eXtensible Intuitive Automatable Tree Language
Project-URL: Homepage, https://codeberg.org/id_est_2817_2/xiatl
Author-email: "id.est.2817.2" <id.est.2817.2@gmail.com>
License-Expression: Apache-2.0
License-File: LICENSE.txt
Classifier: Operating System :: OS Independent
Classifier: Programming Language :: Python :: 3
Requires-Python: >=3.9
